{
  "activity": {
    "resource_state": 3,
    "athlete": {
      "id": 5019,
      "resource_state": 1
    },
    "name": "Morning Ride",
    "distance": 2513.1,
    "moving_time": 437,
    "elapsed_time": 437,
    "total_elevation_gain": 8.0,
    "type": "Ride",
    "sport_type": "Ride",
    "workout_type": 10,
    "device_name": "Garmin Edge 840",
    "id": 18583008588,
    "start_date": "2026-05-20T15:14:14Z",
    "start_date_local": "2026-05-20T08:14:14Z",
    "timezone": "(GMT-08:00) America/Los_Angeles",
    "utc_offset": -25200.0,
    "location_city": null,
    "location_state": null,
    "location_country": null,
    "achievement_count": 0,
    "kudos_count": 0,
    "comment_count": 0,
    "athlete_count": 1,
    "photo_count": 0,
    "map": {
      "id": "a18583008588",
      "polyline": "we`cF|{dhV@EAKGGICaAAcFDeBCaF@ICGGCM?[@kGAmEBsEBgBC}@QoA?eANcAz@yCJa@Da@DgIEyAGe@@IBEHAn@?BABIAGIGm@DUGKFADJr@FbBCvGAt@Y|Aw@lCIv@@v@P`BB`ABXEd@CtACfQBlABJNNHDVB|A?vEHzB@tC@\\ADJCZ",
      "resource_state": 3,
      "summary_polyline": ""
    },
    "trainer": false,
    "commute": true,
    "manual": false,
    "private": true,
    "visibility": "only_me",
    "flagged": false,
    "gear_id": "b10625923",
    "start_latlng": [],
    "end_latlng": [],
    "average_speed": 5.751,
    "max_speed": 8.0,
    "average_cadence": 85.2,
    "average_temp": 21,
    "average_watts": 92.2,
    "max_watts": 360,
    "weighted_average_watts": 98,
    "device_watts": true,
    "kilojoules": 39.6,
    "has_heartrate": true,
    "average_heartrate": 112.6,
    "max_heartrate": 130.0,
    "heartrate_opt_out": false,
    "display_hide_heartrate_option": true,
    "elev_high": 59.2,
    "elev_low": 53.6,
    "upload_id": 19689390104,
    "upload_id_str": "19689390104",
    "external_id": "garmin_ping_573873796187",
    "from_accepted_tag": false,
    "pr_count": 0,
    "total_photo_count": 0,
    "has_kudoed": false,
    "description": "",
    "calories": 49.0,
    "perceived_exertion": null,
    "prefer_perceived_exertion": false,
    "segment_efforts": [],
    "splits_metric": [
      {
        "distance": 1000.3,
        "elapsed_time": 156,
        "elevation_difference": -2.6,
        "moving_time": 156,
        "split": 1,
        "average_speed": 6.41,
        "average_grade_adjusted_speed": 6.39,
        "average_heartrate": 104.12582781456953,
        "pace_zone": 0
      },
      {
        "distance": 1006.5,
        "elapsed_time": 190,
        "elevation_difference": -0.4,
        "moving_time": 190,
        "split": 2,
        "average_speed": 5.3,
        "average_grade_adjusted_speed": 5.31,
        "average_heartrate": 113.68852459016394,
        "pace_zone": 0
      },
      {
        "distance": 506.3,
        "elapsed_time": 91,
        "elevation_difference": 4.4,
        "moving_time": 91,
        "split": 3,
        "average_speed": 5.56,
        "average_grade_adjusted_speed": 5.71,
        "average_heartrate": 124.37777777777778,
        "pace_zone": 0
      }
    ],
    "splits_standard": [
      {
        "distance": 1616.7,
        "elapsed_time": 278,
        "elevation_difference": -2.6,
        "moving_time": 278,
        "split": 1,
        "average_speed": 5.82,
        "average_grade_adjusted_speed": 5.81,
        "average_heartrate": 107.20074349442379,
        "pace_zone": 0
      },
      {
        "distance": 896.4,
        "elapsed_time": 159,
        "elevation_difference": 4.0,
        "moving_time": 159,
        "split": 2,
        "average_speed": 5.64,
        "average_grade_adjusted_speed": 5.72,
        "average_heartrate": 121.83870967741936,
        "pace_zone": 0
      }
    ],
    "laps": [
      {
        "id": 66481108267,
        "resource_state": 2,
        "name": "Lap 1",
        "activity": {
          "id": 18583008588,
          "visibility": "only_me",
          "resource_state": 1
        },
        "athlete": {
          "id": 5019,
          "resource_state": 1
        },
        "elapsed_time": 436,
        "moving_time": 436,
        "start_date": "2026-05-20T15:14:14Z",
        "start_date_local": "2026-05-20T08:14:14Z",
        "distance": 2513.15,
        "average_speed": 5.76,
        "max_speed": 8.0,
        "lap_index": 1,
        "split": 1,
        "start_index": 0,
        "end_index": 0,
        "total_elevation_gain": 9.6,
        "average_cadence": 85.2,
        "device_watts": true,
        "average_watts": 92.2,
        "average_heartrate": 112.6,
        "max_heartrate": 130.0
      }
    ],
    "gear": {
      "id": "b10625923",
      "primary": false,
      "name": "Strong 2",
      "nickname": "Strong 2",
      "resource_state": 2,
      "retired": false,
      "distance": 24174831,
      "converted_distance": 15021.5
    },
    "photos": {
      "primary": null,
      "count": 0
    },
    "stats_visibility": [
      {
        "type": "heart_rate",
        "visibility": "everyone"
      },
      {
        "type": "pace",
        "visibility": "everyone"
      },
      {
        "type": "power",
        "visibility": "everyone"
      },
      {
        "type": "speed",
        "visibility": "everyone"
      },
      {
        "type": "calories",
        "visibility": "everyone"
      }
    ],
    "hide_from_home": false,
    "embed_token": "e8649d4ab351a9d785097ee785b03f3519d86978",
    "available_zones": []
  },
  "streams": {
    "altitude": {
      "data": [
        57.8,
        57.8,
        57.8,
        57.8,
        58.0,
        58.0,
        58.0,
        58.0,
        58.0,
        58.0,
        58.0,
        58.2,
        58.2,
        58.2,
        58.2,
        58.2,
        58.0,
        58.0,
        57.8,
        57.8,
        57.8,
        57.8,
        57.6,
        57.6,
        57.4,
        57.4,
        57.4,
        57.4,
        57.2,
        57.0,
        57.0,
        56.8,
        56.6,
        56.4,
        56.4,
        56.4,
        56.4,
        56.2,
        56.2,
        56.2,
        56.0,
        56.0,
        56.0,
        56.0,
        56.0,
        55.8,
        55.6,
        55.6,
        55.4,
        55.4,
        55.4,
        55.4,
        55.2,
        55.2,
        55.2,
        55.2,
        55.2,
        55.2,
        55.0,
        55.0,
        55.0,
        54.8,
        54.8,
        54.6,
        54.6,
        54.6,
        54.6,
        54.6,
        54.6,
        54.6,
        54.6,
        54.6,
        54.6,
        54.4,
        54.4,
        54.4,
        54.4,
        54.4,
        54.4,
        54.4,
        54.6,
        54.4,
        54.4,
        54.2,
        54.4,
        54.4,
        54.4,
        54.6,
        54.8,
        54.6,
        54.6,
        54.8,
        55.0,
        55.0,
        55.2,
        55.4,
        55.4,
        55.4,
        55.4,
        55.4,
        55.4,
        55.4,
        55.4,
        55.6,
        55.6,
        55.8,
        55.8,
        55.8,
        56.0,
        56.0,
        56.0,
        56.0,
        56.0,
        56.0,
        56.0,
        56.0,
        56.0,
        56.0,
        56.2,
        56.0,
        56.0,
        55.8,
        56.0,
        55.8,
        55.6,
        55.6,
        55.6,
        55.4,
        55.4,
        55.4,
        55.2,
        55.2,
        55.2,
        55.2,
        55.2,
        55.2,
        55.0,
        55.0,
        55.0,
        55.2,
        55.0,
        55.0,
        55.0,
        55.0,
        55.0,
        55.0,
        55.0,
        55.0,
        55.0,
        55.0,
        55.0,
        55.0,
        55.0,
        55.0,
        55.0,
        55.2,
        55.2,
        55.2,
        55.2,
        55.0,
        55.0,
        54.8,
        54.8,
        54.8,
        54.8,
        54.8,
        54.6,
        54.6,
        54.6,
        54.6,
        54.4,
        54.4,
        54.4,
        54.2,
        54.2,
        54.2,
        54.2,
        54.2,
        54.0,
        54.0,
        54.0,
        54.0,
        54.0,
        53.8,
        53.8,
        53.6,
        53.6,
        53.6,
        53.6,
        53.6,
        53.6,
        53.8,
        53.8,
        53.8,
        53.8,
        54.0,
        54.0,
        54.0,
        54.2,
        54.2,
        54.2,
        54.2,
        54.4,
        54.4,
        54.4,
        54.4,
        54.4,
        54.4,
        54.4,
        54.4,
        54.4,
        54.4,
        54.4,
        54.4,
        54.4,
        54.4,
        54.2,
        54.2,
        54.2,
        54.2,
        54.0,
        54.0,
        53.8,
        53.8,
        53.6,
        53.6,
        53.6,
        53.6,
        53.8,
        53.8,
        53.8,
        54.0,
        54.0,
        54.0,
        54.0,
        54.2,
        54.2,
        54.2,
        54.2,
        54.4,
        54.4,
        54.4,
        54.6,
        54.6,
        54.6,
        54.6,
        54.6,
        54.6,
        54.6,
        54.8,
        54.8,
        54.8,
        54.8,
        55.0,
        55.0,
        55.0,
        55.0,
        55.0,
        55.0,
        55.0,
        55.2,
        55.2,
        55.2,
        55.2,
        55.2,
        55.2,
        55.2,
        55.2,
        55.4,
        55.4,
        55.4,
        55.4,
        55.4,
        55.4,
        55.2,
        55.2,
        55.2,
        55.2,
        55.2,
        55.2,
        55.2,
        55.2,
        55.2,
        55.4,
        55.4,
        55.4,
        55.2,
        55.2,
        55.2,
        55.2,
        55.2,
        55.2,
        55.2,
        55.2,
        55.4,
        55.4,
        55.4,
        55.4,
        55.6,
        55.6,
        55.6,
        55.6,
        55.8,
        55.8,
        55.8,
        56.0,
        56.0,
        56.0,
        56.0,
        56.0,
        56.0,
        56.0,
        56.0,
        55.8,
        56.0,
        56.0,
        56.0,
        56.0,
        56.2,
        56.2,
        56.0,
        56.0,
        56.0,
        56.0,
        55.8,
        55.6,
        55.6,
        55.6,
        55.4,
        55.4,
        55.6,
        55.6,
        55.6,
        55.8,
        55.8,
        55.8,
        55.6,
        55.6,
        55.4,
        55.4,
        55.2,
        55.2,
        55.0,
        55.0,
        55.0,
        54.8,
        54.8,
        54.8,
        54.8,
        54.6,
        54.6,
        54.6,
        54.6,
        54.4,
        54.4,
        54.4,
        54.4,
        54.2,
        54.2,
        54.2,
        54.4,
        54.4,
        54.6,
        54.8,
        54.8,
        54.6,
        54.6,
        54.6,
        54.6,
        54.6,
        54.4,
        54.4,
        54.4,
        54.6,
        54.6,
        55.0,
        55.0,
        55.0,
        55.2,
        55.2,
        55.2,
        55.2,
        55.4,
        55.2,
        55.2,
        55.4,
        55.4,
        55.4,
        55.4,
        55.4,
        55.4,
        55.4,
        55.4,
        55.6,
        55.6,
        55.8,
        55.8,
        56.0,
        56.0,
        56.0,
        56.0,
        56.2,
        56.2,
        56.4,
        56.4,
        56.6,
        56.6,
        56.8,
        56.8,
        56.8,
        57.0,
        57.2,
        57.2,
        57.2,
        57.2,
        57.2,
        57.4,
        57.4,
        57.6,
        57.6,
        57.6,
        57.6,
        57.8,
        57.8,
        58.0,
        58.2,
        58.2,
        58.4,
        58.4,
        58.4,
        58.6,
        58.8,
        58.8,
        58.8,
        59.0,
        59.2,
        59.2,
        59.2
      ],
      "series_type": "distance",
      "original_size": 438,
      "resolution": "high"
    },
    "latlng": {
      "data": [
        [
          37.361725,
          -122.091023
        ],
        [
          37.361725,
          -122.091023
        ],
        [
          37.361725,
          -122.091023
        ],
        [
          37.361725,
          -122.091023
        ],
        [
          37.361725,
          -122.091023
        ],
        [
          37.361711,
          -122.090991
        ],
        [
          37.361715,
          -122.090962
        ],
        [
          37.361726,
          -122.090936
        ],
        [
          37.361743,
          -122.090914
        ],
        [
          37.361761,
          -122.090892
        ],
        [
          37.361788,
          -122.090882
        ],
        [
          37.361819,
          -122.090877
        ],
        [
          37.361856,
          -122.090881
        ],
        [
          37.361894,
          -122.090881
        ],
        [
          37.361934,
          -122.090881
        ],
        [
          37.361979,
          -122.09088
        ],
        [
          37.362032,
          -122.090878
        ],
        [
          37.362087,
          -122.090873
        ],
        [
          37.362143,
          -122.09087
        ],
        [
          37.362203,
          -122.090874
        ],
        [
          37.362263,
          -122.090878
        ],
        [
          37.362325,
          -122.09088
        ],
        [
          37.362389,
          -122.090878
        ],
        [
          37.362456,
          -122.090879
        ],
        [
          37.362524,
          -122.090885
        ],
        [
          37.362594,
          -122.090889
        ],
        [
          37.362663,
          -122.090889
        ],
        [
          37.36273,
          -122.090886
        ],
        [
          37.3628,
          -122.090888
        ],
        [
          37.362871,
          -122.090888
        ],
        [
          37.362939,
          -122.090892
        ],
        [
          37.363009,
          -122.090889
        ],
        [
          37.363078,
          -122.090887
        ],
        [
          37.363147,
          -122.090885
        ],
        [
          37.363215,
          -122.090889
        ],
        [
          37.363282,
          -122.090897
        ],
        [
          37.363349,
          -122.090896
        ],
        [
          37.363414,
          -122.090893
        ],
        [
          37.363477,
          -122.09089
        ],
        [
          37.363542,
          -122.090883
        ],
        [
          37.363606,
          -122.090876
        ],
        [
          37.363669,
          -122.090872
        ],
        [
          37.36373,
          -122.090872
        ],
        [
          37.363792,
          -122.090871
        ],
        [
          37.363854,
          -122.090872
        ],
        [
          37.363916,
          -122.090872
        ],
        [
          37.363982,
          -122.09087
        ],
        [
          37.364046,
          -122.090872
        ],
        [
          37.364108,
          -122.090876
        ],
        [
          37.36417,
          -122.090878
        ],
        [
          37.36423,
          -122.090874
        ],
        [
          37.364293,
          -122.090871
        ],
        [
          37.364356,
          -122.090875
        ],
        [
          37.364419,
          -122.09088
        ],
        [
          37.364481,
          -122.090877
        ],
        [
          37.364544,
          -122.090874
        ],
        [
          37.364608,
          -122.090872
        ],
        [
          37.364673,
          -122.090873
        ],
        [
          37.364738,
          -122.090874
        ],
        [
          37.364801,
          -122.090879
        ],
        [
          37.364861,
          -122.090883
        ],
        [
          37.364924,
          -122.090885
        ],
        [
          37.364976,
          -122.090864
        ],
        [
          37.365014,
          -122.090821
        ],
        [
          37.365032,
          -122.090759
        ],
        [
          37.365036,
          -122.090691
        ],
        [
          37.365039,
          -122.090618
        ],
        [
          37.365037,
          -122.090544
        ],
        [
          37.365036,
          -122.090467
        ],
        [
          37.365037,
          -122.09039
        ],
        [
          37.365037,
          -122.090312
        ],
        [
          37.365038,
          -122.090231
        ],
        [
          37.365039,
          -122.09015
        ],
        [
          37.365035,
          -122.090068
        ],
        [
          37.365034,
          -122.089989
        ],
        [
          37.365033,
          -122.089907
        ],
        [
          37.365033,
          -122.089826
        ],
        [
          37.365034,
          -122.089744
        ],
        [
          37.365034,
          -122.089664
        ],
        [
          37.365034,
          -122.089586
        ],
        [
          37.365034,
          -122.08951
        ],
        [
          37.365033,
          -122.089434
        ],
        [
          37.36503,
          -122.089355
        ],
        [
          37.365025,
          -122.089274
        ],
        [
          37.365025,
          -122.089194
        ],
        [
          37.365025,
          -122.089113
        ],
        [
          37.365028,
          -122.089032
        ],
        [
          37.365029,
          -122.08895
        ],
        [
          37.365029,
          -122.088869
        ],
        [
          37.365027,
          -122.088789
        ],
        [
          37.365026,
          -122.08871
        ],
        [
          37.365027,
          -122.088633
        ],
        [
          37.365028,
          -122.088555
        ],
        [
          37.365029,
          -122.088476
        ],
        [
          37.365029,
          -122.0884
        ],
        [
          37.365031,
          -122.088325
        ],
        [
          37.365032,
          -122.08825
        ],
        [
          37.365031,
          -122.088174
        ],
        [
          37.36503,
          -122.088095
        ],
        [
          37.36503,
          -122.088017
        ],
        [
          37.365029,
          -122.087941
        ],
        [
          37.365027,
          -122.087864
        ],
        [
          37.365025,
          -122.087787
        ],
        [
          37.365023,
          -122.087709
        ],
        [
          37.365022,
          -122.087634
        ],
        [
          37.365023,
          -122.087557
        ],
        [
          37.365022,
          -122.087484
        ],
        [
          37.365021,
          -122.08741
        ],
        [
          37.36502,
          -122.087341
        ],
        [
          37.36502,
          -122.087277
        ],
        [
          37.365019,
          -122.087222
        ],
        [
          37.365019,
          -122.087184
        ],
        [
          37.365018,
          -122.087163
        ],
        [
          37.365017,
          -122.087143
        ],
        [
          37.365013,
          -122.087124
        ],
        [
          37.365013,
          -122.087095
        ],
        [
          37.365008,
          -122.087054
        ],
        [
          37.365006,
          -122.087004
        ],
        [
          37.365001,
          -122.086944
        ],
        [
          37.364999,
          -122.086878
        ],
        [
          37.364993,
          -122.086807
        ],
        [
          37.364989,
          -122.086735
        ],
        [
          37.36499,
          -122.086661
        ],
        [
          37.364993,
          -122.086587
        ],
        [
          37.364996,
          -122.086514
        ],
        [
          37.365005,
          -122.086436
        ],
        [
          37.365016,
          -122.086356
        ],
        [
          37.365034,
          -122.086278
        ],
        [
          37.365056,
          -122.086201
        ],
        [
          37.365076,
          -122.086123
        ],
        [
          37.365091,
          -122.086039
        ],
        [
          37.365102,
          -122.085955
        ],
        [
          37.36511,
          -122.085867
        ],
        [
          37.365114,
          -122.085779
        ],
        [
          37.365114,
          -122.085691
        ],
        [
          37.365109,
          -122.085602
        ],
        [
          37.365095,
          -122.085516
        ],
        [
          37.365077,
          -122.085432
        ],
        [
          37.365053,
          -122.085349
        ],
        [
          37.365027,
          -122.085269
        ],
        [
          37.364997,
          -122.085191
        ],
        [
          37.364966,
          -122.085117
        ],
        [
          37.364939,
          -122.08504
        ],
        [
          37.36491,
          -122.084963
        ],
        [
          37.36488,
          -122.084888
        ],
        [
          37.36485,
          -122.084811
        ],
        [
          37.364821,
          -122.084732
        ],
        [
          37.364791,
          -122.084653
        ],
        [
          37.364756,
          -122.084574
        ],
        [
          37.364723,
          -122.084494
        ],
        [
          37.364696,
          -122.084413
        ],
        [
          37.36467,
          -122.084329
        ],
        [
          37.364649,
          -122.084243
        ],
        [
          37.364635,
          -122.084153
        ],
        [
          37.364627,
          -122.084063
        ],
        [
          37.364623,
          -122.083975
        ],
        [
          37.364623,
          -122.083888
        ],
        [
          37.364624,
          -122.0838
        ],
        [
          37.364624,
          -122.083716
        ],
        [
          37.364621,
          -122.083628
        ],
        [
          37.364619,
          -122.083539
        ],
        [
          37.364616,
          -122.083449
        ],
        [
          37.364613,
          -122.083358
        ],
        [
          37.364611,
          -122.083268
        ],
        [
          37.364608,
          -122.083178
        ],
        [
          37.364607,
          -122.08309
        ],
        [
          37.364607,
          -122.083004
        ],
        [
          37.364606,
          -122.08292
        ],
        [
          37.364608,
          -122.082838
        ],
        [
          37.364608,
          -122.082755
        ],
        [
          37.364605,
          -122.082675
        ],
        [
          37.364604,
          -122.082593
        ],
        [
          37.364605,
          -122.082512
        ],
        [
          37.364608,
          -122.082432
        ],
        [
          37.364612,
          -122.082355
        ],
        [
          37.364616,
          -122.082282
        ],
        [
          37.364622,
          -122.08221
        ],
        [
          37.36463,
          -122.082137
        ],
        [
          37.364637,
          -122.082065
        ],
        [
          37.364648,
          -122.081994
        ],
        [
          37.364662,
          -122.081927
        ],
        [
          37.364674,
          -122.081871
        ],
        [
          37.364667,
          -122.081827
        ],
        [
          37.364647,
          -122.081793
        ],
        [
          37.36462,
          -122.081786
        ],
        [
          37.364591,
          -122.081782
        ],
        [
          37.36456,
          -122.081783
        ],
        [
          37.36453,
          -122.081783
        ],
        [
          37.364505,
          -122.081783
        ],
        [
          37.364482,
          -122.081784
        ],
        [
          37.364463,
          -122.081787
        ],
        [
          37.364444,
          -122.081788
        ],
        [
          37.364423,
          -122.081791
        ],
        [
          37.364399,
          -122.08179
        ],
        [
          37.364377,
          -122.081788
        ],
        [
          37.364353,
          -122.081785
        ],
        [
          37.364332,
          -122.081773
        ],
        [
          37.364321,
          -122.081756
        ],
        [
          37.364317,
          -122.08173
        ],
        [
          37.364317,
          -122.081717
        ],
        [
          37.364319,
          -122.081709
        ],
        [
          37.364317,
          -122.081704
        ],
        [
          37.364317,
          -122.081704
        ],
        [
          37.364317,
          -122.081704
        ],
        [
          37.364317,
          -122.081704
        ],
        [
          37.364323,
          -122.081682
        ],
        [
          37.364337,
          -122.081668
        ],
        [
          37.364353,
          -122.081656
        ],
        [
          37.36437,
          -122.081647
        ],
        [
          37.364388,
          -122.081643
        ],
        [
          37.364408,
          -122.081649
        ],
        [
          37.364436,
          -122.081656
        ],
        [
          37.364467,
          -122.081663
        ],
        [
          37.3645,
          -122.081667
        ],
        [
          37.364535,
          -122.08167
        ],
        [
          37.36457,
          -122.081671
        ],
        [
          37.364604,
          -122.081671
        ],
        [
          37.364632,
          -122.081665
        ],
        [
          37.364656,
          -122.081657
        ],
        [
          37.364681,
          -122.081646
        ],
        [
          37.364712,
          -122.081639
        ],
        [
          37.364741,
          -122.081649
        ],
        [
          37.36477,
          -122.081674
        ],
        [
          37.364787,
          -122.08171
        ],
        [
          37.364782,
          -122.081751
        ],
        [
          37.364765,
          -122.081796
        ],
        [
          37.364752,
          -122.081848
        ],
        [
          37.364737,
          -122.081908
        ],
        [
          37.364727,
          -122.081969
        ],
        [
          37.364721,
          -122.082032
        ],
        [
          37.364714,
          -122.082093
        ],
        [
          37.364706,
          -122.082158
        ],
        [
          37.364701,
          -122.082222
        ],
        [
          37.364698,
          -122.082283
        ],
        [
          37.364694,
          -122.082344
        ],
        [
          37.364687,
          -122.082406
        ],
        [
          37.364681,
          -122.082469
        ],
        [
          37.364682,
          -122.082531
        ],
        [
          37.364685,
          -122.082595
        ],
        [
          37.364683,
          -122.082661
        ],
        [
          37.364683,
          -122.082724
        ],
        [
          37.364681,
          -122.082787
        ],
        [
          37.364683,
          -122.082852
        ],
        [
          37.364686,
          -122.082915
        ],
        [
          37.364687,
          -122.082979
        ],
        [
          37.364688,
          -122.083045
        ],
        [
          37.36469,
          -122.083112
        ],
        [
          37.36469,
          -122.083182
        ],
        [
          37.364689,
          -122.08325
        ],
        [
          37.36469,
          -122.083314
        ],
        [
          37.364691,
          -122.083384
        ],
        [
          37.364694,
          -122.083455
        ],
        [
          37.364698,
          -122.083526
        ],
        [
          37.3647,
          -122.083599
        ],
        [
          37.364699,
          -122.083669
        ],
        [
          37.3647,
          -122.083736
        ],
        [
          37.364699,
          -122.083804
        ],
        [
          37.3647,
          -122.083868
        ],
        [
          37.364702,
          -122.083935
        ],
        [
          37.364703,
          -122.084003
        ],
        [
          37.364711,
          -122.084069
        ],
        [
          37.364718,
          -122.084135
        ],
        [
          37.364731,
          -122.084203
        ],
        [
          37.364747,
          -122.084271
        ],
        [
          37.364766,
          -122.08434
        ],
        [
          37.364786,
          -122.084408
        ],
        [
          37.364805,
          -122.084474
        ],
        [
          37.364828,
          -122.084539
        ],
        [
          37.36485,
          -122.084605
        ],
        [
          37.364874,
          -122.084671
        ],
        [
          37.364899,
          -122.084736
        ],
        [
          37.364924,
          -122.0848
        ],
        [
          37.364949,
          -122.084867
        ],
        [
          37.364975,
          -122.084929
        ],
        [
          37.365001,
          -122.08499
        ],
        [
          37.365028,
          -122.085052
        ],
        [
          37.365054,
          -122.085112
        ],
        [
          37.365079,
          -122.085177
        ],
        [
          37.365105,
          -122.085247
        ],
        [
          37.365129,
          -122.085314
        ],
        [
          37.365147,
          -122.085383
        ],
        [
          37.36516,
          -122.085449
        ],
        [
          37.365169,
          -122.085521
        ],
        [
          37.365173,
          -122.085593
        ],
        [
          37.365173,
          -122.085664
        ],
        [
          37.365173,
          -122.085732
        ],
        [
          37.365172,
          -122.085804
        ],
        [
          37.365169,
          -122.085875
        ],
        [
          37.36516,
          -122.085942
        ],
        [
          37.365151,
          -122.086015
        ],
        [
          37.365138,
          -122.086084
        ],
        [
          37.365121,
          -122.086154
        ],
        [
          37.365104,
          -122.086221
        ],
        [
          37.365089,
          -122.086291
        ],
        [
          37.365077,
          -122.086363
        ],
        [
          37.365068,
          -122.086432
        ],
        [
          37.365059,
          -122.0865
        ],
        [
          37.365057,
          -122.086566
        ],
        [
          37.36506,
          -122.086633
        ],
        [
          37.365057,
          -122.0867
        ],
        [
          37.365049,
          -122.086754
        ],
        [
          37.365038,
          -122.086795
        ],
        [
          37.365035,
          -122.086826
        ],
        [
          37.365041,
          -122.086852
        ],
        [
          37.365045,
          -122.086873
        ],
        [
          37.365045,
          -122.086887
        ],
        [
          37.365046,
          -122.086895
        ],
        [
          37.365046,
          -122.086895
        ],
        [
          37.365046,
          -122.086895
        ],
        [
          37.365046,
          -122.086895
        ],
        [
          37.365046,
          -122.086895
        ],
        [
          37.365048,
          -122.086925
        ],
        [
          37.365055,
          -122.086964
        ],
        [
          37.365061,
          -122.087012
        ],
        [
          37.365065,
          -122.087062
        ],
        [
          37.365068,
          -122.087117
        ],
        [
          37.36507,
          -122.087176
        ],
        [
          37.365072,
          -122.087239
        ],
        [
          37.365075,
          -122.087305
        ],
        [
          37.365081,
          -122.087373
        ],
        [
          37.365087,
          -122.087444
        ],
        [
          37.365088,
          -122.087518
        ],
        [
          37.365087,
          -122.087593
        ],
        [
          37.365086,
          -122.087664
        ],
        [
          37.365083,
          -122.087738
        ],
        [
          37.365082,
          -122.087812
        ],
        [
          37.365082,
          -122.087891
        ],
        [
          37.365082,
          -122.087972
        ],
        [
          37.365083,
          -122.088058
        ],
        [
          37.365084,
          -122.088145
        ],
        [
          37.365083,
          -122.08823
        ],
        [
          37.365083,
          -122.088315
        ],
        [
          37.365086,
          -122.0884
        ],
        [
          37.365087,
          -122.088486
        ],
        [
          37.365088,
          -122.088573
        ],
        [
          37.365088,
          -122.088658
        ],
        [
          37.365087,
          -122.088743
        ],
        [
          37.365088,
          -122.08883
        ],
        [
          37.36509,
          -122.088916
        ],
        [
          37.36509,
          -122.089002
        ],
        [
          37.36509,
          -122.089087
        ],
        [
          37.36509,
          -122.08917
        ],
        [
          37.365091,
          -122.089254
        ],
        [
          37.365092,
          -122.089338
        ],
        [
          37.365095,
          -122.089422
        ],
        [
          37.365098,
          -122.089507
        ],
        [
          37.365098,
          -122.089592
        ],
        [
          37.365095,
          -122.089677
        ],
        [
          37.365093,
          -122.089761
        ],
        [
          37.365091,
          -122.089845
        ],
        [
          37.365092,
          -122.089932
        ],
        [
          37.365093,
          -122.090019
        ],
        [
          37.365097,
          -122.090103
        ],
        [
          37.365101,
          -122.090186
        ],
        [
          37.365103,
          -122.090273
        ],
        [
          37.365104,
          -122.090361
        ],
        [
          37.365099,
          -122.090445
        ],
        [
          37.365094,
          -122.090527
        ],
        [
          37.365089,
          -122.090609
        ],
        [
          37.365089,
          -122.090688
        ],
        [
          37.365089,
          -122.090757
        ],
        [
          37.365067,
          -122.090818
        ],
        [
          37.365032,
          -122.090861
        ],
        [
          37.364987,
          -122.090897
        ],
        [
          37.364934,
          -122.090924
        ],
        [
          37.364877,
          -122.090939
        ],
        [
          37.364819,
          -122.090944
        ],
        [
          37.36476,
          -122.090944
        ],
        [
          37.364701,
          -122.090945
        ],
        [
          37.364641,
          -122.090945
        ],
        [
          37.364579,
          -122.090947
        ],
        [
          37.364517,
          -122.090946
        ],
        [
          37.364458,
          -122.090944
        ],
        [
          37.364398,
          -122.090943
        ],
        [
          37.364341,
          -122.090942
        ],
        [
          37.364285,
          -122.090944
        ],
        [
          37.36423,
          -122.090947
        ],
        [
          37.364175,
          -122.090956
        ],
        [
          37.364121,
          -122.090958
        ],
        [
          37.364066,
          -122.090959
        ],
        [
          37.364011,
          -122.090962
        ],
        [
          37.363954,
          -122.090962
        ],
        [
          37.363899,
          -122.090965
        ],
        [
          37.363844,
          -122.090965
        ],
        [
          37.36379,
          -122.090966
        ],
        [
          37.363736,
          -122.090968
        ],
        [
          37.363683,
          -122.090968
        ],
        [
          37.36363,
          -122.090969
        ],
        [
          37.363578,
          -122.090973
        ],
        [
          37.363526,
          -122.090975
        ],
        [
          37.363474,
          -122.090977
        ],
        [
          37.363424,
          -122.09098
        ],
        [
          37.363372,
          -122.090984
        ],
        [
          37.36332,
          -122.090987
        ],
        [
          37.363269,
          -122.090991
        ],
        [
          37.363223,
          -122.09099
        ],
        [
          37.363174,
          -122.090988
        ],
        [
          37.363125,
          -122.090987
        ],
        [
          37.363075,
          -122.090989
        ],
        [
          37.363028,
          -122.090992
        ],
        [
          37.362981,
          -122.090993
        ],
        [
          37.362934,
          -122.090996
        ],
        [
          37.362884,
          -122.090996
        ],
        [
          37.362836,
          -122.090996
        ],
        [
          37.362792,
          -122.090996
        ],
        [
          37.362746,
          -122.090998
        ],
        [
          37.362697,
          -122.090999
        ],
        [
          37.362649,
          -122.091003
        ],
        [
          37.362599,
          -122.091003
        ],
        [
          37.362549,
          -122.091003
        ],
        [
          37.362498,
          -122.091002
        ],
        [
          37.362449,
          -122.091004
        ],
        [
          37.362398,
          -122.091005
        ],
        [
          37.36235,
          -122.091006
        ],
        [
          37.362302,
          -122.091007
        ],
        [
          37.362253,
          -122.091007
        ],
        [
          37.362204,
          -122.091007
        ],
        [
          37.362159,
          -122.091005
        ],
        [
          37.362111,
          -122.091005
        ],
        [
          37.362064,
          -122.091005
        ],
        [
          37.362019,
          -122.091006
        ],
        [
          37.361977,
          -122.091011
        ],
        [
          37.361935,
          -122.091013
        ],
        [
          37.361892,
          -122.091015
        ],
        [
          37.361853,
          -122.091013
        ],
        [
          37.361816,
          -122.091007
        ],
        [
          37.36178,
          -122.091
        ],
        [
          37.361747,
          -122.091003
        ],
        [
          37.361724,
          -122.091025
        ],
        [
          37.361713,
          -122.091065
        ],
        [
          37.361712,
          -122.091092
        ],
        [
          37.361715,
          -122.091125
        ],
        [
          37.361727,
          -122.091141
        ],
        [
          37.361737,
          -122.091154
        ],
        [
          37.361738,
          -122.091177
        ],
        [
          37.361738,
          -122.091192
        ],
        [
          37.361736,
          -122.091204
        ],
        [
          37.361736,
          -122.09121
        ]
      ],
      "series_type": "distance",
      "original_size": 438,
      "resolution": "high"
    },
    "watts": {
      "data": [
        0,
        0,
        0,
        0,
        0,
        0,
        0,
        0,
        0,
        0,
        0,
        0,
        0,
        0,
        0,
        0,
        0,
        128,
        103,
        105,
        131,
        113,
        105,
        128,
        131,
        188,
        119,
        86,
        72,
        64,
        58,
        66,
        50,
        47,
        44,
        46,
        52,
        45,
        58,
        64,
        69,
        83,
        83,
        72,
        72,
        77,
        72,
        81,
        78,
        62,
        64,
        70,
        70,
        62,
        51,
        54,
        53,
        49,
        0,
        0,
        0,
        0,
        0,
        0,
        0,
        0,
        270,
        147,
        147,
        130,
        184,
        141,
        109,
        110,
        102,
        81,
        94,
        108,
        97,
        121,
        134,
        132,
        153,
        231,
        242,
        215,
        226,
        179,
        130,
        136,
        117,
        117,
        173,
        171,
        182,
        134,
        143,
        145,
        153,
        103,
        86,
        96,
        96,
        125,
        131,
        142,
        94,
        68,
        0,
        0,
        0,
        0,
        0,
        0,
        0,
        0,
        95,
        347,
        296,
        221,
        233,
        146,
        67,
        87,
        87,
        86,
        128,
        159,
        144,
        175,
        175,
        213,
        169,
        101,
        98,
        85,
        71,
        71,
        83,
        93,
        95,
        95,
        93,
        107,
        117,
        123,
        193,
        168,
        177,
        186,
        173,
        133,
        112,
        114,
        88,
        79,
        98,
        108,
        107,
        87,
        97,
        105,
        118,
        39,
        24,
        0,
        0,
        0,
        0,
        46,
        50,
        11,
        11,
        28,
        0,
        0,
        0,
        0,
        0,
        0,
        0,
        0,
        0,
        0,
        0,
        0,
        142,
        173,
        0,
        0,
        0,
        0,
        0,
        75,
        140,
        27,
        13,
        13,
        9,
        9,
        0,
        0,
        0,
        0,
        0,
        0,
        0,
        0,
        0,
        0,
        0,
        6,
        151,
        0,
        0,
        0,
        0,
        0,
        0,
        0,
        0,
        0,
        28,
        274,
        53,
        233,
        289,
        239,
        167,
        104,
        94,
        92,
        92,
        91,
        95,
        96,
        131,
        173,
        160,
        82,
        80,
        92,
        91,
        90,
        89,
        120,
        168,
        118,
        120,
        109,
        115,
        104,
        119,
        83,
        101,
        109,
        120,
        129,
        146,
        125,
        104,
        88,
        94,
        107,
        131,
        102,
        84,
        77,
        82,
        74,
        84,
        88,
        101,
        96,
        104,
        118,
        100,
        89,
        102,
        102,
        124,
        120,
        128,
        187,
        187,
        124,
        132,
        103,
        113,
        99,
        110,
        111,
        107,
        95,
        90,
        94,
        106,
        98,
        91,
        10,
        4,
        4,
        0,
        0,
        0,
        11,
        0,
        0,
        0,
        0,
        0,
        0,
        102,
        360,
        289,
        318,
        208,
        196,
        145,
        228,
        155,
        88,
        90,
        98,
        102,
        103,
        149,
        188,
        185,
        207,
        130,
        129,
        103,
        103,
        111,
        99,
        81,
        82,
        76,
        64,
        66,
        64,
        74,
        66,
        73,
        84,
        79,
        84,
        120,
        147,
        154,
        154,
        161,
        134,
        142,
        156,
        167,
        157,
        128,
        0,
        0,
        0,
        13,
        197,
        299,
        194,
        151,
        114,
        114,
        113,
        183,
        152,
        134,
        133,
        133,
        117,
        96,
        86,
        101,
        125,
        109,
        102,
        124,
        112,
        95,
        95,
        82,
        95,
        92,
        93,
        98,
        117,
        136,
        94,
        89,
        101,
        112,
        106,
        119,
        125,
        101,
        117,
        143,
        124,
        127,
        136,
        113,
        100,
        96,
        92,
        121,
        185,
        188,
        135,
        88,
        109,
        107,
        102,
        108,
        119,
        104,
        73,
        36,
        36,
        118,
        73,
        0,
        0,
        0,
        0,
        0,
        16,
        70,
        15,
        15,
        0,
        0,
        0
      ],
      "series_type": "distance",
      "original_size": 438,
      "resolution": "high"
    },
    "cadence": {
      "data": [
        92,
        92,
        92,
        92,
        92,
        92,
        92,
        92,
        92,
        92,
        92,
        92,
        92,
        92,
        92,
        92,
        92,
        92,
        96,
        94,
        100,
        102,
        101,
        106,
        96,
        96,
        98,
        97,
        96,
        96,
        96,
        99,
        95,
        96,
        95,
        95,
        91,
        93,
        94,
        92,
        91,
        91,
        89,
        89,
        90,
        89,
        89,
        88,
        91,
        89,
        89,
        89,
        90,
        90,
        91,
        91,
        92,
        90,
        90,
        90,
        0,
        0,
        0,
        0,
        0,
        8,
        88,
        88,
        102,
        103,
        104,
        104,
        91,
        92,
        93,
        95,
        89,
        90,
        92,
        90,
        89,
        88,
        85,
        91,
        90,
        100,
        95,
        93,
        93,
        90,
        89,
        89,
        86,
        88,
        89,
        88,
        87,
        85,
        89,
        91,
        86,
        86,
        87,
        89,
        82,
        85,
        88,
        85,
        63,
        63,
        63,
        0,
        18,
        18,
        18,
        0,
        26,
        76,
        88,
        87,
        97,
        98,
        99,
        99,
        100,
        103,
        104,
        103,
        92,
        92,
        95,
        98,
        101,
        102,
        100,
        101,
        100,
        99,
        100,
        98,
        95,
        94,
        99,
        95,
        100,
        97,
        97,
        102,
        91,
        92,
        89,
        92,
        88,
        88,
        91,
        90,
        89,
        88,
        91,
        91,
        89,
        90,
        92,
        84,
        89,
        89,
        89,
        0,
        15,
        87,
        87,
        87,
        49,
        77,
        77,
        77,
        0,
        13,
        13,
        13,
        0,
        0,
        0,
        0,
        8,
        8,
        51,
        68,
        68,
        68,
        0,
        0,
        13,
        44,
        53,
        42,
        42,
        49,
        49,
        43,
        43,
        43,
        0,
        0,
        0,
        8,
        8,
        8,
        0,
        0,
        0,
        10,
        68,
        68,
        68,
        0,
        0,
        0,
        0,
        0,
        7,
        7,
        32,
        78,
        45,
        90,
        91,
        91,
        96,
        94,
        95,
        95,
        95,
        95,
        95,
        95,
        93,
        96,
        100,
        94,
        100,
        99,
        102,
        98,
        96,
        94,
        90,
        93,
        91,
        90,
        91,
        90,
        93,
        91,
        91,
        91,
        92,
        91,
        93,
        92,
        95,
        92,
        91,
        92,
        93,
        94,
        93,
        95,
        93,
        96,
        94,
        92,
        98,
        97,
        94,
        96,
        95,
        95,
        93,
        93,
        93,
        93,
        93,
        93,
        95,
        94,
        97,
        97,
        95,
        95,
        96,
        97,
        97,
        91,
        96,
        94,
        94,
        91,
        91,
        61,
        61,
        29,
        29,
        29,
        0,
        17,
        17,
        17,
        0,
        0,
        0,
        11,
        42,
        75,
        86,
        96,
        93,
        97,
        93,
        92,
        95,
        100,
        99,
        99,
        98,
        102,
        101,
        107,
        88,
        94,
        98,
        100,
        94,
        94,
        95,
        100,
        96,
        97,
        99,
        97,
        98,
        94,
        97,
        94,
        99,
        97,
        99,
        95,
        95,
        97,
        97,
        98,
        98,
        96,
        94,
        98,
        97,
        99,
        100,
        100,
        100,
        0,
        13,
        78,
        94,
        96,
        100,
        100,
        99,
        97,
        101,
        101,
        100,
        100,
        99,
        102,
        93,
        94,
        93,
        93,
        91,
        90,
        91,
        86,
        92,
        89,
        90,
        89,
        87,
        87,
        85,
        87,
        95,
        96,
        94,
        92,
        92,
        93,
        91,
        94,
        92,
        91,
        94,
        93,
        92,
        92,
        94,
        91,
        92,
        90,
        89,
        91,
        95,
        96,
        96,
        91,
        94,
        91,
        90,
        90,
        90,
        91,
        91,
        25,
        85,
        92,
        92,
        92,
        0,
        0,
        0,
        19,
        68,
        68,
        50,
        50,
        0,
        0
      ],
      "series_type": "distance",
      "original_size": 438,
      "resolution": "high"
    },
    "time": {
      "data": [
        0,
        1,
        2,
        3,
        4,
        5,
        6,
        7,
        8,
        9,
        10,
        11,
        12,
        13,
        14,
        15,
        16,
        17,
        18,
        19,
        20,
        21,
        22,
        23,
        24,
        25,
        26,
        27,
        28,
        29,
        30,
        31,
        32,
        33,
        34,
        35,
        36,
        37,
        38,
        39,
        40,
        41,
        42,
        43,
        44,
        45,
        46,
        47,
        48,
        49,
        50,
        51,
        52,
        53,
        54,
        55,
        56,
        57,
        58,
        59,
        60,
        61,
        62,
        63,
        64,
        65,
        66,
        67,
        68,
        69,
        70,
        71,
        72,
        73,
        74,
        75,
        76,
        77,
        78,
        79,
        80,
        81,
        82,
        83,
        84,
        85,
        86,
        87,
        88,
        89,
        90,
        91,
        92,
        93,
        94,
        95,
        96,
        97,
        98,
        99,
        100,
        101,
        102,
        103,
        104,
        105,
        106,
        107,
        108,
        109,
        110,
        111,
        112,
        113,
        114,
        115,
        116,
        117,
        118,
        119,
        120,
        121,
        122,
        123,
        124,
        125,
        126,
        127,
        128,
        129,
        130,
        131,
        132,
        133,
        134,
        135,
        136,
        137,
        138,
        139,
        140,
        141,
        142,
        143,
        144,
        145,
        146,
        147,
        148,
        149,
        150,
        151,
        152,
        153,
        154,
        155,
        156,
        157,
        158,
        159,
        160,
        161,
        162,
        163,
        164,
        165,
        166,
        167,
        168,
        169,
        170,
        171,
        172,
        173,
        174,
        175,
        176,
        177,
        178,
        179,
        180,
        181,
        182,
        183,
        184,
        185,
        186,
        187,
        188,
        189,
        190,
        191,
        192,
        193,
        194,
        195,
        196,
        197,
        198,
        199,
        200,
        201,
        202,
        203,
        204,
        205,
        206,
        207,
        208,
        209,
        210,
        211,
        212,
        213,
        214,
        215,
        216,
        217,
        218,
        219,
        220,
        221,
        222,
        223,
        224,
        225,
        226,
        227,
        228,
        229,
        230,
        231,
        232,
        233,
        234,
        235,
        236,
        237,
        238,
        239,
        240,
        241,
        242,
        243,
        244,
        245,
        246,
        247,
        248,
        249,
        250,
        251,
        252,
        253,
        254,
        255,
        256,
        257,
        258,
        259,
        260,
        261,
        262,
        263,
        264,
        265,
        266,
        267,
        268,
        269,
        270,
        271,
        272,
        273,
        274,
        275,
        276,
        277,
        278,
        279,
        280,
        281,
        282,
        283,
        284,
        285,
        286,
        287,
        288,
        289,
        290,
        291,
        292,
        293,
        294,
        295,
        296,
        297,
        298,
        299,
        300,
        301,
        302,
        303,
        304,
        305,
        306,
        307,
        308,
        309,
        310,
        311,
        312,
        313,
        314,
        315,
        316,
        317,
        318,
        319,
        320,
        321,
        322,
        323,
        324,
        325,
        326,
        327,
        328,
        329,
        330,
        331,
        332,
        333,
        334,
        335,
        336,
        337,
        338,
        339,
        340,
        341,
        342,
        343,
        344,
        345,
        346,
        347,
        348,
        349,
        350,
        351,
        352,
        353,
        354,
        355,
        356,
        357,
        358,
        359,
        360,
        361,
        362,
        363,
        364,
        365,
        366,
        367,
        368,
        369,
        370,
        371,
        372,
        373,
        374,
        375,
        376,
        377,
        378,
        379,
        380,
        381,
        382,
        383,
        384,
        385,
        386,
        387,
        388,
        389,
        390,
        391,
        392,
        393,
        394,
        395,
        396,
        397,
        398,
        399,
        400,
        401,
        402,
        403,
        404,
        405,
        406,
        407,
        408,
        409,
        410,
        411,
        412,
        413,
        414,
        415,
        416,
        417,
        418,
        419,
        420,
        421,
        422,
        423,
        424,
        425,
        426,
        427,
        428,
        429,
        430,
        431,
        432,
        433,
        434,
        435,
        436,
        437
      ],
      "series_type": "distance",
      "original_size": 438,
      "resolution": "high"
    },
    "heartrate": {
      "data": [
        0,
        0,
        0,
        0,
        0,
        0,
        0,
        0,
        0,
        0,
        0,
        0,
        0,
        0,
        0,
        0,
        0,
        92,
        92,
        92,
        93,
        93,
        94,
        94,
        95,
        95,
        97,
        98,
        100,
        102,
        103,
        105,
        107,
        108,
        108,
        108,
        108,
        108,
        108,
        108,
        108,
        109,
        109,
        109,
        109,
        110,
        110,
        110,
        110,
        110,
        110,
        110,
        110,
        110,
        110,
        110,
        110,
        110,
        110,
        110,
        110,
        109,
        109,
        109,
        108,
        108,
        107,
        107,
        107,
        107,
        107,
        108,
        108,
        108,
        108,
        109,
        109,
        109,
        110,
        110,
        111,
        111,
        111,
        110,
        110,
        110,
        110,
        110,
        110,
        111,
        111,
        112,
        112,
        112,
        113,
        113,
        114,
        114,
        114,
        115,
        115,
        116,
        116,
        117,
        117,
        117,
        117,
        117,
        117,
        117,
        116,
        116,
        115,
        114,
        113,
        113,
        113,
        113,
        113,
        113,
        113,
        113,
        114,
        115,
        116,
        117,
        118,
        118,
        119,
        120,
        121,
        122,
        122,
        123,
        123,
        123,
        124,
        124,
        125,
        125,
        126,
        126,
        126,
        126,
        126,
        125,
        125,
        124,
        124,
        124,
        124,
        124,
        124,
        124,
        124,
        124,
        124,
        125,
        125,
        126,
        126,
        126,
        125,
        125,
        124,
        124,
        123,
        123,
        122,
        122,
        121,
        120,
        119,
        118,
        117,
        117,
        117,
        117,
        117,
        118,
        119,
        119,
        118,
        118,
        117,
        117,
        117,
        116,
        114,
        113,
        112,
        111,
        110,
        108,
        107,
        106,
        104,
        102,
        102,
        102,
        102,
        102,
        102,
        101,
        101,
        101,
        100,
        100,
        99,
        99,
        99,
        100,
        100,
        100,
        100,
        101,
        101,
        100,
        100,
        100,
        100,
        99,
        99,
        99,
        99,
        99,
        99,
        99,
        99,
        99,
        100,
        100,
        100,
        101,
        102,
        104,
        105,
        107,
        108,
        107,
        107,
        107,
        107,
        107,
        107,
        109,
        111,
        112,
        112,
        113,
        112,
        112,
        112,
        112,
        112,
        113,
        113,
        113,
        113,
        114,
        114,
        115,
        116,
        117,
        117,
        117,
        117,
        117,
        117,
        118,
        118,
        119,
        119,
        120,
        120,
        120,
        120,
        120,
        119,
        119,
        118,
        118,
        118,
        118,
        118,
        118,
        118,
        119,
        119,
        119,
        120,
        120,
        119,
        119,
        119,
        119,
        118,
        118,
        118,
        118,
        118,
        117,
        117,
        117,
        117,
        117,
        117,
        117,
        117,
        117,
        116,
        116,
        115,
        114,
        113,
        113,
        113,
        112,
        112,
        113,
        114,
        114,
        115,
        116,
        117,
        118,
        118,
        118,
        119,
        119,
        119,
        119,
        120,
        120,
        121,
        121,
        122,
        122,
        122,
        123,
        123,
        123,
        124,
        124,
        124,
        124,
        124,
        124,
        124,
        123,
        123,
        123,
        123,
        123,
        123,
        123,
        123,
        123,
        123,
        123,
        122,
        122,
        122,
        122,
        122,
        122,
        122,
        123,
        123,
        124,
        124,
        124,
        125,
        125,
        126,
        127,
        127,
        127,
        128,
        128,
        129,
        129,
        130,
        130,
        130,
        130,
        130,
        129,
        129,
        129,
        128,
        129,
        129,
        129,
        129,
        129,
        128,
        128,
        128,
        127,
        126,
        126,
        126,
        125,
        125,
        125,
        124,
        124,
        124,
        125,
        125,
        125,
        125,
        125,
        125,
        124,
        124,
        123,
        123,
        122,
        122,
        122,
        122,
        122,
        122,
        122,
        121,
        121,
        121,
        120,
        119,
        118,
        118,
        117,
        117,
        117,
        117,
        117
      ],
      "series_type": "distance",
      "original_size": 438,
      "resolution": "high"
    },
    "distance": {
      "data": [
        0.0,
        0.0,
        0.0,
        0.0,
        0.0,
        0.3,
        2.2,
        4.1,
        6.1,
        8.3,
        11.1,
        14.9,
        19.1,
        23.9,
        28.7,
        33.9,
        39.6,
        45.6,
        51.9,
        58.3,
        65.0,
        71.7,
        78.7,
        85.8,
        93.1,
        100.5,
        108.1,
        115.6,
        123.1,
        130.7,
        138.1,
        145.6,
        153.1,
        160.6,
        167.9,
        175.3,
        182.7,
        189.9,
        197.0,
        204.1,
        211.0,
        218.0,
        225.1,
        232.1,
        239.1,
        246.1,
        253.0,
        259.9,
        266.9,
        273.9,
        280.8,
        287.8,
        294.9,
        301.9,
        309.0,
        316.1,
        323.1,
        330.1,
        337.1,
        344.0,
        350.7,
        357.3,
        363.6,
        369.9,
        376.1,
        382.3,
        388.7,
        395.4,
        402.1,
        408.9,
        415.9,
        423.1,
        430.2,
        437.3,
        444.5,
        451.6,
        458.8,
        465.8,
        472.8,
        479.8,
        486.8,
        493.6,
        500.5,
        507.6,
        514.8,
        522.1,
        529.4,
        536.6,
        543.7,
        550.7,
        557.6,
        564.5,
        571.3,
        578.2,
        585.0,
        591.8,
        598.6,
        605.5,
        612.4,
        619.3,
        626.1,
        632.9,
        639.7,
        646.3,
        653.0,
        659.6,
        666.2,
        672.8,
        679.0,
        685.0,
        690.2,
        694.5,
        697.5,
        699.3,
        701.0,
        703.2,
        706.8,
        711.2,
        716.7,
        722.4,
        728.7,
        735.2,
        741.8,
        748.5,
        755.2,
        762.1,
        769.0,
        776.2,
        783.5,
        790.8,
        798.4,
        806.2,
        814.0,
        821.8,
        829.6,
        837.4,
        845.1,
        852.9,
        860.5,
        868.1,
        875.6,
        883.1,
        890.7,
        898.2,
        905.7,
        913.5,
        921.3,
        929.1,
        937.0,
        945.0,
        952.9,
        960.8,
        968.8,
        976.7,
        984.7,
        992.5,
        1000.3,
        1008.3,
        1016.3,
        1024.2,
        1032.2,
        1040.3,
        1048.2,
        1056.2,
        1064.1,
        1072.0,
        1079.6,
        1087.0,
        1094.4,
        1101.8,
        1109.1,
        1116.3,
        1123.4,
        1130.3,
        1137.0,
        1143.7,
        1150.1,
        1156.4,
        1162.6,
        1168.8,
        1174.9,
        1180.4,
        1184.6,
        1188.6,
        1191.9,
        1195.1,
        1198.5,
        1202.0,
        1205.3,
        1208.0,
        1210.5,
        1212.7,
        1214.8,
        1217.1,
        1219.8,
        1222.5,
        1224.9,
        1227.4,
        1229.8,
        1232.1,
        1234.3,
        1234.3,
        1234.3,
        1234.3,
        1234.3,
        1234.8,
        1236.5,
        1238.4,
        1240.4,
        1242.5,
        1244.8,
        1247.5,
        1250.9,
        1254.6,
        1258.2,
        1261.9,
        1265.8,
        1269.3,
        1272.4,
        1275.4,
        1278.3,
        1281.9,
        1285.1,
        1289.0,
        1292.9,
        1297.8,
        1303.1,
        1308.6,
        1314.1,
        1319.7,
        1325.2,
        1330.7,
        1336.2,
        1341.7,
        1347.2,
        1352.8,
        1358.3,
        1364.0,
        1369.8,
        1375.5,
        1381.3,
        1387.0,
        1392.8,
        1398.4,
        1404.1,
        1409.8,
        1415.9,
        1422.0,
        1428.0,
        1434.1,
        1440.1,
        1446.2,
        1452.5,
        1458.7,
        1464.7,
        1470.9,
        1477.1,
        1483.2,
        1489.5,
        1495.7,
        1501.7,
        1507.9,
        1514.1,
        1520.3,
        1526.4,
        1532.6,
        1538.9,
        1545.3,
        1551.5,
        1557.8,
        1564.2,
        1570.5,
        1576.9,
        1583.3,
        1589.6,
        1596.0,
        1602.3,
        1608.6,
        1616.7,
        1621.0,
        1627.2,
        1633.4,
        1639.6,
        1646.1,
        1652.6,
        1659.1,
        1665.5,
        1671.9,
        1678.2,
        1684.6,
        1691.0,
        1697.4,
        1703.8,
        1710.2,
        1716.6,
        1722.8,
        1728.9,
        1735.1,
        1741.1,
        1746.9,
        1751.6,
        1755.8,
        1759.3,
        1761.9,
        1763.8,
        1765.8,
        1765.8,
        1766.9,
        1768.1,
        1768.1,
        1768.1,
        1768.5,
        1771.8,
        1776.0,
        1780.8,
        1786.0,
        1791.4,
        1797.2,
        1803.2,
        1809.6,
        1816.1,
        1822.7,
        1829.3,
        1835.9,
        1842.5,
        1849.3,
        1856.2,
        1863.4,
        1870.9,
        1878.3,
        1885.8,
        1893.2,
        1900.7,
        1908.3,
        1915.8,
        1923.4,
        1931.0,
        1938.6,
        1946.2,
        1953.8,
        1961.3,
        1968.9,
        1976.5,
        1984.0,
        1991.7,
        1999.3,
        2006.8,
        2014.4,
        2021.9,
        2029.4,
        2036.9,
        2044.4,
        2052.0,
        2059.6,
        2067.1,
        2074.6,
        2082.2,
        2089.7,
        2096.9,
        2103.8,
        2109.9,
        2115.5,
        2121.1,
        2127.0,
        2133.4,
        2139.9,
        2146.5,
        2153.2,
        2159.9,
        2166.5,
        2173.2,
        2179.9,
        2186.5,
        2193.1,
        2199.6,
        2206.0,
        2212.3,
        2218.4,
        2224.6,
        2230.7,
        2236.8,
        2242.8,
        2248.8,
        2254.8,
        2260.8,
        2266.8,
        2272.7,
        2278.6,
        2284.3,
        2290.1,
        2295.9,
        2301.7,
        2307.4,
        2312.9,
        2318.3,
        2323.7,
        2329.0,
        2334.3,
        2339.7,
        2345.1,
        2350.4,
        2355.8,
        2361.3,
        2366.7,
        2372.1,
        2377.5,
        2382.9,
        2388.2,
        2393.6,
        2398.8,
        2404.0,
        2409.4,
        2415.0,
        2420.5,
        2426.0,
        2431.4,
        2436.8,
        2442.1,
        2447.3,
        2452.6,
        2457.7,
        2462.5,
        2467.1,
        2471.6,
        2476.1,
        2480.5,
        2484.5,
        2488.1,
        2491.8,
        2495.6,
        2499.3,
        2502.4,
        2505.3,
        2507.7,
        2509.7,
        2511.4,
        2513.1,
        2513.1
      ],
      "series_type": "distance",
      "original_size": 438,
      "resolution": "high"
    }
  }
}